RunFeemsSim/__init__.py
RunFeemsSim/_modidx.py
RunFeemsSim/_nbdev.py
RunFeemsSim/machinery_calculation.py
RunFeemsSim/pms_basic.py
RunFeemsSim/py.typed
runfeemssim-0.2.6.dist-info/licenses/LICENSE
runfeemssim-0.2.6.dist-info/METADATA
runfeemssim-0.2.6.dist-info/WHEEL
runfeemssim-0.2.6.dist-info/top_level.txt
runfeemssim-0.2.6.dist-info/RECORD
