Metadata-Version: 2.4
Name: RunFeemsSim
Version: 0.2.6
Summary: A library for running feems simulation
Home-page: https://github.com/SINTEF/FEEMS
Author: Kevin Koosup Yum
Author-email: kevinkoosup.yum@sintef.no
License: Apache Software License 2.0
Keywords: FEEMS,machinery system,fuel,emissions
Classifier: Development Status :: 3 - Alpha
Classifier: Intended Audience :: Developers
Classifier: Natural Language :: English
Classifier: Programming Language :: Python :: 3.10
Classifier: License :: OSI Approved :: Apache Software License
Requires-Python: >=3.10
License-File: LICENSE
Requires-Dist: pip
Requires-Dist: packaging
Requires-Dist: pandas
Requires-Dist: numpy
Requires-Dist: MachSysS
Provides-Extra: dev
Dynamic: author
Dynamic: author-email
Dynamic: classifier
Dynamic: description
Dynamic: description-content-type
Dynamic: home-page
Dynamic: keywords
Dynamic: license
Dynamic: license-file
Dynamic: provides-extra
Dynamic: requires-dist
Dynamic: requires-python
Dynamic: summary
